zsp_fe_parser/core.cpython-38-x86_64-linux-gnu.so
zsp_fe_parser/__version__.py
zsp_fe_parser/libzsp-fe-parser.so
zsp_fe_parser/pkginfo.py
zsp_fe_parser/__build_num__.py
zsp_fe_parser/__init__.py
zsp_fe_parser/share/include/zsp/fe/parser/IAst2ArlContext.h
zsp_fe_parser/share/include/zsp/fe/parser/IFactory.h
zsp_fe_parser/share/include/zsp/fe/parser/IAst2ArlBuilder.h
zsp_fe_parser/share/include/zsp/fe/parser/IElemFactoryAssocData.h
zsp_fe_parser/share/include/zsp/fe/parser/FactoryExt.h
zsp_fe_parser/share/include/zsp/fe/parser/impl/TaskIsTopDownScope.h
zsp_fe_parser/share/include/zsp/fe/parser/impl/ElemFactoryAssocDataBase.h
zuspec_fe_parser-0.0.5.dist-info/LICENSE
zuspec_fe_parser-0.0.5.dist-info/WHEEL
zuspec_fe_parser-0.0.5.dist-info/RECORD
zuspec_fe_parser-0.0.5.dist-info/top_level.txt
zuspec_fe_parser-0.0.5.dist-info/entry_points.txt
zuspec_fe_parser-0.0.5.dist-info/METADATA
